lbpextract/__init__.py
lbpextract/parser.py
lbpextract-0.2.2.dist-info/LICENSE
lbpextract-0.2.2.dist-info/METADATA
lbpextract-0.2.2.dist-info/WHEEL
lbpextract-0.2.2.dist-info/entry_points.txt
lbpextract-0.2.2.dist-info/top_level.txt
lbpextract-0.2.2.dist-info/RECORD
