Metadata-Version: 2.2
Name: lbpextract
Version: 0.2.2
Summary: A tool to convert La Banque Postale's account documents (PDFs) into CSV files.
Home-page: https://github.com/hayj/LBPExtract
Author: hayj
License-File: LICENSE
Requires-Dist: pandas
Requires-Dist: systools
Requires-Dist: PyMuPDF<=1.24.0
Requires-Dist: tqdm
